autocorns/DarkForest.py
autocorns/ERC721.py
autocorns/ERC721WithDiamondStorage.py
autocorns/MetadataFacet.py
autocorns/StatsFacet.py
autocorns/__init__.py
autocorns/biologist.py
autocorns/cli.py
autocorns/warden.py
autocorns/build/contracts/DarkForest.json
autocorns/build/contracts/ERC721.json
autocorns/build/contracts/ERC721WithDiamondStorage.json
autocorns/build/contracts/MetadataFacet.json
autocorns/build/contracts/StatsFacet.json
autocorns-0.0.7.dist-info/LICENSE
autocorns-0.0.7.dist-info/METADATA
autocorns-0.0.7.dist-info/WHEEL
autocorns-0.0.7.dist-info/entry_points.txt
autocorns-0.0.7.dist-info/top_level.txt
autocorns-0.0.7.dist-info/RECORD
