Metadata-Version: 2.1
Name: autocorns
Version: 0.0.7
Summary: A team of Crypto Unicorn bots
Home-page: https://github.com/zomglings/autocorns
Author: zomglings
Author-email: nkashy1@gmail.com
License: UNKNOWN
Platform: UNKNOWN
Classifier: Development Status :: 3 - Alpha
Classifier: Programming Language :: Python
Requires-Python: >=3.6
Requires-Dist: eth-brownie
Requires-Dist: requests
Requires-Dist: tqdm
Requires-Dist: web3
Provides-Extra: dev
Requires-Dist: black ; extra == 'dev'
Requires-Dist: moonworm (>=0.1.14) ; extra == 'dev'
Provides-Extra: distribute
Requires-Dist: setuptools ; extra == 'distribute'
Requires-Dist: twine ; extra == 'distribute'
Requires-Dist: wheel ; extra == 'distribute'
